tinyvec/__init__.py
tinyvec/array2d.py
tinyvec/langchain_store.py
tinyvec/localization.py
tinyvec/vector_db.py
tinyvec-2024.2.10.dist-info/METADATA
tinyvec-2024.2.10.dist-info/WHEEL
tinyvec-2024.2.10.dist-info/top_level.txt
tinyvec-2024.2.10.dist-info/RECORD
