Metadata-Version: 2.1
Name: tinyvec
Version: 2024.2.10
Summary: A learning experience in vector databases
Author-email: Xander May <x@whoelsebut.me>
License: MIT License
Project-URL: Homepage, https://tinyvec.whoelsebut.me
Project-URL: Documentation, https://github.com/xmaayy/tinyvec
Project-URL: Repository, https://github.com/xmaayy/tinyvec
Project-URL: Bug Tracker, https://github.com/xmaayy/tinyvec/issues
Project-URL: Changelog, https://github.com/xmaayy/tinyvec/blob/master/CHANGELOG.md
Keywords: vector,database,embedding,locality hashing
Classifier: Development Status :: 3 - Alpha
Classifier: Programming Language :: Python
Classifier: License :: OSI Approved :: MIT License
Classifier: Operating System :: OS Independent
Requires-Python: >=3.10
Requires-Dist: numpy
Provides-Extra: dev
Requires-Dist: pytest ; extra == 'dev'
Requires-Dist: pytest-cov ; extra == 'dev'
Requires-Dist: langchain ; extra == 'dev'
Provides-Extra: langchain
Requires-Dist: langchain ; extra == 'langchain'
